jupyter_shelf/__init__.py
jupyter_shelf/app.py
jupyter_shelf-0.0.5.dist-info/LICENSE
jupyter_shelf-0.0.5.dist-info/METADATA
jupyter_shelf-0.0.5.dist-info/WHEEL
jupyter_shelf-0.0.5.dist-info/entry_points.txt
jupyter_shelf-0.0.5.dist-info/top_level.txt
jupyter_shelf-0.0.5.dist-info/RECORD
