Metadata-Version: 2.1
Name: jupyter_shelf
Version: 0.0.5
Summary: A CLI tool to manage virtual environments for jupyter notebooks
Author-email: habanoz <huseyinabanox@gmail.com>
Project-URL: Homepage, https://github.com/habanoz/jupyter_shelf
Project-URL: Issues, https://github.com/habanoz/jupyter_shelf/issues
Classifier: Programming Language :: Python :: 3
Classifier: License :: OSI Approved :: MIT License
Classifier: Operating System :: OS Independent
Requires-Python: >=3.8
License-File: LICENSE
